[
  {
    "name": "Midtown",
    "borough": "Manhattan",
    "center": {
      "lat": 40.7549,
      "lng": -73.984
    },
    "avgMinutes": 16.8
  },
  {
    "name": "West Village",
    "borough": "Manhattan",
    "center": {
      "lat": 40.7336,
      "lng": -74.0027
    },
    "avgMinutes": 17.7
  },
  {
    "name": "SoHo",
    "borough": "Manhattan",
    "center": {
      "lat": 40.7233,
      "lng": -73.9985
    },
    "avgMinutes": 19.8
  },
  {
    "name": "Tribeca",
    "borough": "Manhattan",
    "center": {
      "lat": 40.7163,
      "lng": -74.0086
    },
    "avgMinutes": 20.2
  },
  {
    "name": "Murray Hill",
    "borough": "Manhattan",
    "center": {
      "lat": 40.7488,
      "lng": -73.9757
    },
    "avgMinutes": 20.3
  },
  {
    "name": "Chelsea",
    "borough": "Manhattan",
    "center": {
      "lat": 40.7465,
      "lng": -74.0014
    },
    "avgMinutes": 21.3
  },
  {
    "name": "Financial District",
    "borough": "Manhattan",
    "center": {
      "lat": 40.7075,
      "lng": -74.0089
    },
    "avgMinutes": 21.4
  },
  {
    "name": "Gramercy",
    "borough": "Manhattan",
    "center": {
      "lat": 40.7368,
      "lng": -73.9845
    },
    "avgMinutes": 21.7
  },
  {
    "name": "East Village",
    "borough": "Manhattan",
    "center": {
      "lat": 40.7265,
      "lng": -73.9815
    },
    "avgMinutes": 24.5
  },
  {
    "name": "Long Island City",
    "borough": "Queens",
    "center": {
      "lat": 40.744,
      "lng": -73.956
    },
    "avgMinutes": 24.7
  },
  {
    "name": "Upper West Side",
    "borough": "Manhattan",
    "center": {
      "lat": 40.787,
      "lng": -73.9754
    },
    "avgMinutes": 25.5
  },
  {
    "name": "Hell's Kitchen",
    "borough": "Manhattan",
    "center": {
      "lat": 40.7638,
      "lng": -73.9918
    },
    "avgMinutes": 26.2
  },
  {
    "name": "DUMBO",
    "borough": "Brooklyn",
    "center": {
      "lat": 40.7033,
      "lng": -73.989
    },
    "avgMinutes": 27.6
  },
  {
    "name": "Lower East Side",
    "borough": "Manhattan",
    "center": {
      "lat": 40.715,
      "lng": -73.9843
    },
    "avgMinutes": 28
  },
  {
    "name": "Greenpoint",
    "borough": "Brooklyn",
    "center": {
      "lat": 40.7274,
      "lng": -73.951
    },
    "avgMinutes": 28
  },
  {
    "name": "Williamsburg",
    "borough": "Brooklyn",
    "center": {
      "lat": 40.7081,
      "lng": -73.9571
    },
    "avgMinutes": 29.1
  },
  {
    "name": "Fort Greene",
    "borough": "Brooklyn",
    "center": {
      "lat": 40.6892,
      "lng": -73.9747
    },
    "avgMinutes": 29.1
  },
  {
    "name": "Prospect Heights",
    "borough": "Brooklyn",
    "center": {
      "lat": 40.6775,
      "lng": -73.9692
    },
    "avgMinutes": 30.5
  },
  {
    "name": "Cobble Hill",
    "borough": "Brooklyn",
    "center": {
      "lat": 40.686,
      "lng": -73.9969
    },
    "avgMinutes": 32.5
  },
  {
    "name": "Harlem",
    "borough": "Manhattan",
    "center": {
      "lat": 40.8116,
      "lng": -73.9465
    },
    "avgMinutes": 33.8
  },
  {
    "name": "Crown Heights",
    "borough": "Brooklyn",
    "center": {
      "lat": 40.6694,
      "lng": -73.9422
    },
    "avgMinutes": 34.7
  },
  {
    "name": "Park Slope",
    "borough": "Brooklyn",
    "center": {
      "lat": 40.671,
      "lng": -73.9777
    },
    "avgMinutes": 37.3
  },
  {
    "name": "Bushwick",
    "borough": "Brooklyn",
    "center": {
      "lat": 40.6942,
      "lng": -73.9215
    },
    "avgMinutes": 41.5
  },
  {
    "name": "Bed-Stuy",
    "borough": "Brooklyn",
    "center": {
      "lat": 40.6872,
      "lng": -73.9418
    },
    "avgMinutes": 41.5
  },
  {
    "name": "Astoria",
    "borough": "Queens",
    "center": {
      "lat": 40.7723,
      "lng": -73.9301
    },
    "avgMinutes": 47.9
  }
]